harness_pywinrm/__init__.py
harness_pywinrm/parsedict.py
harness_pywinrm/pywinrm.py
harness_pywinrm-0.4.4.dist-info/LICENSE
harness_pywinrm-0.4.4.dist-info/METADATA
harness_pywinrm-0.4.4.dist-info/WHEEL
harness_pywinrm-0.4.4.dist-info/entry_points.txt
harness_pywinrm-0.4.4.dist-info/top_level.txt
harness_pywinrm-0.4.4.dist-info/RECORD
