Metadata-Version: 2.1
Name: harness-pywinrm
Version: 0.4.4
Summary: CLI for Windows Remote Management
Home-page: https://harness0.harness.io/ng/account/l7B_kbSEQD2wjrM7PShm5w/module/code/orgs/PROD/projects/Harness_Commons/repos/winrm-kerberos-pywinrm
Author: Harness.io
Author-email: ivan.mijailovic@harness.io
License: Free To Use But Restricted
Classifier: Programming Language :: Python :: 3
Classifier: License :: Free To Use But Restricted
Classifier: Operating System :: OS Independent
Requires-Python: >=3.8
License-File: LICENSE
Requires-Dist: pykerberos
Requires-Dist: pywinrm
Provides-Extra: test
Requires-Dist: unittest; extra == "test"
